ufile/__init__.py
ufile/exception.py
ufile/file.py
ufile/folder.py
ufile/ufile.py
ufile.io-1.0.2.dist-info/LICENSE
ufile.io-1.0.2.dist-info/METADATA
ufile.io-1.0.2.dist-info/WHEEL
ufile.io-1.0.2.dist-info/top_level.txt
ufile.io-1.0.2.dist-info/RECORD
