Metadata-Version: 2.1
Name: ufile.io
Version: 1.0.2
Summary: Asynchronous Python Wrapper for the Ufile API
Home-page: https://github.com/gautamajay52/ufile.io
Author: gautamajay52
Author-email: gautamajay52@gmail.com
License: MIT
Project-URL: Source, https://github.com/gautamajay52/ufile.io
Project-URL: Documentation, https://github.com/gautamajay52/ufile.io#readme
Project-URL: Tracker, https://github.com/gautamajay52/ufile.io/issues
Keywords: API ufile ufile.io fileuploader storage python
Platform: UNKNOWN
Classifier: Development Status :: 5 - Production/Stable
Classifier: Intended Audience :: Developers
Classifier: License :: OSI Approved :: MIT License
Classifier: Operating System :: OS Independent
Classifier: Programming Language :: Python :: 3.6
Classifier: Programming Language :: Python :: 3.7
Classifier: Programming Language :: Python :: 3.8
Classifier: Programming Language :: Python :: 3.9
Classifier: Topic :: Internet
Requires-Python: >=3.6
License-File: LICENSE
Requires-Dist: aiohttp
